string_path_search/__init__.py
string_path_search/__main__.py
string_path_search/scanner.py
string_path_search/utils.py
string_path_search-0.3.3.dist-info/LICENSE
string_path_search-0.3.3.dist-info/LICENSE-Pillow
string_path_search-0.3.3.dist-info/LICENSE-XlsxWriter
string_path_search-0.3.3.dist-info/METADATA
string_path_search-0.3.3.dist-info/WHEEL
string_path_search-0.3.3.dist-info/entry_points.txt
string_path_search-0.3.3.dist-info/top_level.txt
string_path_search-0.3.3.dist-info/RECORD
