Metadata-Version: 2.1
Name: string-path-search
Version: 0.3.3
Summary: Search a directory path for any of a list of strings.
Home-page: https://github.com/j-lawrence-b1/string_path_search
Author: Larry Barnett
Author-email: JLawrenceB1@gmail.com
License: MIT
Platform: UNKNOWN
Classifier: License :: OSI Approved :: MIT License
Classifier: Programming Language :: Python
Classifier: Programming Language :: Python :: 3
Classifier: Programming Language :: Python :: 3.6
Classifier: Programming Language :: Python :: Implementation :: CPython
Classifier: Programming Language :: Python :: Implementation :: PyPy
Requires-Python: >=3.4.0
Requires-Dist: Pillow
Requires-Dist: xlrd
Requires-Dist: xlsxwriter
